pgsync/__init__.py
pgsync/base.py
pgsync/constants.py
pgsync/exc.py
pgsync/helper.py
pgsync/node.py
pgsync/plugin.py
pgsync/querybuilder.py
pgsync/redisqueue.py
pgsync/search_client.py
pgsync/settings.py
pgsync/singleton.py
pgsync/sync.py
pgsync/transform.py
pgsync/trigger.py
pgsync/urls.py
pgsync/utils.py
pgsync/view.py
pgsync-7.0.5.data/scripts/bootstrap
pgsync-7.0.5.data/scripts/parallel_sync
pgsync-7.0.5.data/scripts/pgsync
pgsync-7.0.5.dist-info/licenses/AUTHORS.rst
pgsync-7.0.5.dist-info/licenses/LICENSE
pgsync-7.0.5.dist-info/METADATA
pgsync-7.0.5.dist-info/WHEEL
pgsync-7.0.5.dist-info/top_level.txt
pgsync-7.0.5.dist-info/RECORD
