Metadata-Version: 2.4
Name: pgsync
Version: 7.0.5
Summary: Postgres/MySQL/MariaDB to Elasticsearch/OpenSearch sync
Home-page: https://github.com/toluaina/pgsync
Author: Tolu Aina
Author-email: tolu@pgsync.com
Maintainer: Tolu Aina
Maintainer-email: tolu@pgsync.com
License: MIT
Project-URL: Bug Reports, https://github.com/toluaina/pgsync/issues
Project-URL: Funding, https://github.com/sponsors/toluaina
Project-URL: Source, https://github.com/toluaina/pgsync
Project-URL: Web, https://pgsync.com
Project-URL: Documentation, https://pgsync.com
Keywords: change data capture,elasticsearch,opensearch,pgsync,postgres,mysql,mariadb
Classifier: Development Status :: 5 - Production/Stable
Classifier: Intended Audience :: Developers
Classifier: Natural Language :: English
Classifier: Programming Language :: Python :: 3.9
Classifier: Programming Language :: Python :: 3.10
Classifier: Programming Language :: Python :: 3.11
Classifier: Programming Language :: Python :: 3.12
Classifier: Programming Language :: Python :: 3.13
Classifier: Programming Language :: Python :: 3.14
Classifier: Programming Language :: Python :: Implementation :: CPython
Classifier: Programming Language :: Python :: Implementation :: PyPy
Classifier: License :: OSI Approved :: MIT License
Classifier: Operating System :: OS Independent
Requires-Python: >=3.9.0
License-File: LICENSE
License-File: AUTHORS.rst
Requires-Dist: async-timeout==5.0.1
Requires-Dist: backports-datetime-fromisoformat==2.0.3
Requires-Dist: boto3==1.42.21
Requires-Dist: botocore==1.42.21
Requires-Dist: certifi==2026.1.4
Requires-Dist: charset-normalizer==3.4.4
Requires-Dist: click==8.1.8
Requires-Dist: elastic-transport==9.1.0
Requires-Dist: elasticsearch==7.17.12
Requires-Dist: elasticsearch-dsl==7.4.1
Requires-Dist: environs==14.4.0
Requires-Dist: events==0.5
Requires-Dist: greenlet==3.2.4
Requires-Dist: idna==3.11
Requires-Dist: jmespath==1.0.1
Requires-Dist: marshmallow==4.0.1
Requires-Dist: mysql-replication==1.0.12
Requires-Dist: opensearch-dsl==2.1.0
Requires-Dist: opensearch-py==3.0.0
Requires-Dist: packaging==25.0
Requires-Dist: psycopg2-binary==2.9.11
Requires-Dist: pymysql==1.1.2
Requires-Dist: python-dateutil==2.9.0.post0
Requires-Dist: python-dotenv==1.2.1
Requires-Dist: redis==7.0.1
Requires-Dist: requests==2.32.5
Requires-Dist: requests-aws4auth==1.3.1
Requires-Dist: s3transfer==0.16.0
Requires-Dist: six==1.17.0
Requires-Dist: sqlalchemy==2.0.45
Requires-Dist: sqlparse==0.5.5
Requires-Dist: typing-extensions==4.15.0
Requires-Dist: urllib3==1.26.20
Dynamic: author
Dynamic: author-email
Dynamic: classifier
Dynamic: description
Dynamic: description-content-type
Dynamic: home-page
Dynamic: keywords
Dynamic: license
Dynamic: license-file
Dynamic: maintainer
Dynamic: maintainer-email
Dynamic: project-url
Dynamic: requires-dist
Dynamic: requires-python
Dynamic: summary
